voicellm/__init__.py
voicellm/__main__.py
voicellm/recognition.py
voicellm/voice_manager.py
voicellm/examples/__init__.py
voicellm/examples/cli_repl.py
voicellm/examples/voice_cli.py
voicellm/examples/web_api.py
voicellm/stt/__init__.py
voicellm/stt/transcriber.py
voicellm/tts/__init__.py
voicellm/tts/tts_engine.py
voicellm/vad/__init__.py
voicellm/vad/voice_detector.py
voicellm-0.2.0.dist-info/licenses/LICENSE
voicellm-0.2.0.dist-info/METADATA
voicellm-0.2.0.dist-info/WHEEL
voicellm-0.2.0.dist-info/entry_points.txt
voicellm-0.2.0.dist-info/top_level.txt
voicellm-0.2.0.dist-info/RECORD
