Metadata-Version: 2.4
Name: voicellm
Version: 0.2.0
Summary: A modular Python library for voice interactions with AI systems
Author-email: Laurent-Philippe Albou <lpalbou@gmail.com>
License-Expression: MIT
Project-URL: Repository, https://github.com/lpalbou/voicellm
Project-URL: Documentation, https://github.com/lpalbou/voicellm#readme
Classifier: Development Status :: 3 - Alpha
Classifier: Intended Audience :: Developers
Classifier: Programming Language :: Python :: 3
Classifier: Programming Language :: Python :: 3.8
Classifier: Programming Language :: Python :: 3.9
Classifier: Programming Language :: Python :: 3.10
Classifier: Programming Language :: Python :: 3.11
Classifier: Programming Language :: Python :: 3.12
Requires-Python: >=3.11.7
License-File: LICENSE
Requires-Dist: numpy>=1.24.0
Requires-Dist: sounddevice>=0.4.6
Requires-Dist: webrtcvad>=2.0.10
Requires-Dist: PyAudio>=0.2.13
Requires-Dist: openai-whisper>=20230314
Requires-Dist: coqui-tts>=0.27.0
Requires-Dist: torch>=2.0.0
Requires-Dist: torchaudio>=2.0.0
Requires-Dist: librosa>=0.10.0
Requires-Dist: soundfile>=0.12.1
Requires-Dist: requests>=2.31.0
Requires-Dist: flask>=2.0.0
Requires-Dist: tiktoken>=0.6.0
Provides-Extra: dev
Requires-Dist: pytest>=7.0.0; extra == "dev"
Requires-Dist: black>=22.0.0; extra == "dev"
Requires-Dist: flake8>=5.0.0; extra == "dev"
Dynamic: license-file
